ctodd_python_lib_exceptions-1.0.0.dist-info/LICENSE.txt
ctodd_python_lib_exceptions-1.0.0.dist-info/METADATA
ctodd_python_lib_exceptions-1.0.0.dist-info/RECORD
ctodd_python_lib_exceptions-1.0.0.dist-info/WHEEL
ctodd_python_lib_exceptions-1.0.0.dist-info/top_level.txt
exception_helpers/__init__.py
exception_helpers/create_exceptions.py
exception_helpers/unsupported_exception.py
exception_helpers/tests/__init__.py
exception_helpers/tests/test_create_exceptions.py
