Metadata-Version: 2.1
Name: ctodd-python-lib-exceptions
Version: 1.0.0
Summary: Python utilities used for handling and raising exceptions
Home-page: https://github.com/ChristopherHaydenTodd/ctodd-python-lib-exceptions
Author: Christopher H. Todd
Author-email: Christopher.Hayden.Todd@gmail.com
License: MIT
Keywords: python,libraries,exceptions
Platform: UNKNOWN
Classifier: Development Status :: 5 - Production/Stable
Classifier: Intended Audience :: Developers
Classifier: Natural Language :: English
Classifier: Programming Language :: Python
Classifier: Programming Language :: Python :: 3
Classifier: Programming Language :: Python :: 3.6
Classifier: Programming Language :: Python :: 3.7
Classifier: Programming Language :: Python :: 3.8
Requires-Python: >3.6
